cmreslogging/__init__.py
cmreslogging/handlers.py
cmreslogging/serializers.py
tests/__init__.py
tests/test_cmreshandler.py
tests/test_cmresserializer.py
CMRESHandler_NtlmAuth-1.1.0.dist-info/LICENSE.md
CMRESHandler_NtlmAuth-1.1.0.dist-info/METADATA
CMRESHandler_NtlmAuth-1.1.0.dist-info/WHEEL
CMRESHandler_NtlmAuth-1.1.0.dist-info/top_level.txt
CMRESHandler_NtlmAuth-1.1.0.dist-info/RECORD
