Metadata-Version: 2.1
Name: CMRESHandler-NtlmAuth
Version: 1.1.0
Summary: Elasticsearch Log handler for the logging library
Home-page: https://github.com/thoscilo/python-elasticsearch-logger/tree/release
Author: Carlos Manzanedo Rueda
Author-email: c.manaha@gmail.com
License: Apache2
Keywords: logging elasticsearch handler log django instrumentation
Classifier: Development Status :: 5 - Production/Stable
Classifier: Intended Audience :: Developers
Classifier: Topic :: System :: Logging
Classifier: Topic :: Software Development :: Libraries
Classifier: Topic :: Internet :: Log Analysis
Classifier: License :: OSI Approved :: Apache Software License
Classifier: Programming Language :: Python :: 3.6
Classifier: Programming Language :: Python :: 3.7
Classifier: Programming Language :: Python :: 3.8
Classifier: Programming Language :: Python :: 3.9
Classifier: Programming Language :: Python :: 3.10
Classifier: Programming Language :: Python :: 3.11
Requires-Python: >=3.6
License-File: LICENSE.md
Requires-Dist: elasticsearch
Requires-Dist: requests
Provides-Extra: dev
Requires-Dist: check-manifest ; extra == 'dev'
Requires-Dist: six ; extra == 'dev'
Requires-Dist: pylint ; extra == 'dev'
Provides-Extra: test
Requires-Dist: coverage ; extra == 'test'
